tema1/siso/design.sv
// Code your design here
// Code your design here

//PIPO


module bistabil_D(input a,input clk,output reg O);
 
  always @(posedge clk)
    begin
      O<=a;
    end
endmodule
/*
module registru(input[3:0] a,input clk, output [3:0] out);
  
  bistabil_D b1(a,clk,out);
  bistabil_D b2(a[2],clk,out[2]);
  bistabil_D b3(a[1],clk,out[1]);
  bistabil_D b4(a[0],clk,out[0]);
endmodule
*/
module registru2(input a,input clk, output  out);
  
  wire out1,out2,out3;
  bistabil_D b1(a,clk,out1);
  bistabil_D b2(out1,clk,out2);
  bistabil_D b3(out2,clk,out3);
  bistabil_D b4(out3,clk,out);
   
 
endmodule

tema1/siso/testbench.sv
// Code your testbench here
// or browse Examples
// Code your testbench here
// or browse Examples


module testbench();
  
  reg clk;
  reg a;
  wire O;
 
  registru2 Ichip1(a,clk,O);
  
  
  
  
  initial clk= 1'b0;
  initial a=1'b1;
  
  initial forever #250 clk = ~clk;
	initial forever #1000 a=~a;
  initial begin
    $dumpfile("dump.vcd");
    $dumpvars;
   
    #9000;
    $finish(1);
  end
  
  
endmodule

tema1/siso/dump.vcd
$date
	Tue Jun 27 15:40:41 2023
$end
$version
	Icarus Verilog
$end
$timescale
	1s
$end
$scope module testbench $end
$var wire 1 ! O $end
$var reg 1 " a $end
$var reg 1 # clk $end
$scope module Ichip1 $end
$var wire 1 $ a $end
$var wire 1 % clk $end
$var wire 1 ! out $end
$var wire 1 & out1 $end
$var wire 1 ' out2 $end
$var wire 1 ( out3 $end
$scope module b1 $end
$var wire 1 $ a $end
$var wire 1 % clk $end
$var reg 1 ) O $end
$upscope $end
$scope module b2 $end
$var wire 1 & a $end
$var wire 1 % clk $end
$var reg 1 * O $end
$upscope $end
$scope module b3 $end
$var wire 1 ' a $end
$var wire 1 % clk $end
$var reg 1 + O $end
$upscope $end
$scope module b4 $end
$var wire 1 ( a $end
$var wire 1 % clk $end
$var reg 1 , O $end
$upscope $end
$upscope $end
$upscope $end
$enddefinitions $end
#0
$dumpvars
x,
x+
x*
x)
x(
x'
x&
0%
1$
0#
1"
x!
$end
#250
1)
1&
1#
1%
#500
0#
0%
#750
1*
1'
1#
1%
#1000
0#
0%
0"
0$
#1250
0)
0&
1+
1(
1#
1%
#1500
0#
0%
#1750
1,
1!
0*
0'
1#
1%
#2000
0#
0%
1"
1$
#2250
1)
1&
0+
0(
1#
1%
#2500
0#
0%
#2750
0,
0!
1*
1'
1#
1%
#3000
0#
0%
0"
0$
#3250
0)
0&
1+
1(
1#
1%
#3500
0#
0%
#3750
1,
1!
0*
0'
1#
1%
#4000
0#
0%
1"
1$
#4250
1)
1&
0+
0(
1#
1%
#4500
0#
0%
#4750
0,
0!
1*
1'
1#
1%
#5000
0#
0%
0"
0$
#5250
0)
0&
1+
1(
1#
1%
#5500
0#
0%
#5750
1,
1!
0*
0'
1#
1%
#6000
0#
0%
1"
1$
#6250
1)
1&
0+
0(
1#
1%
#6500
0#
0%
#6750
0,
0!
1*
1'
1#
1%
#7000
0#
0%
0"
0$
#7250
0)
0&
1+
1(
1#
1%
#7500
0#
0%
#7750
1,
1!
0*
0'
1#
1%
#8000
0#
0%
1"
1$
#8250
1)
1&
0+
0(
1#
1%
#8500
0#
0%
#8750
0,
0!
1*
1'
1#
1%
#9000
0#
0%
0"
0$
