tema1/pipo/design.sv
// Code your design here

//PIPO

/*
module bistabil_D(input a,input clk,output reg O);
 
  always @(posedge clk)
    begin
      O<=a;
    end
endmodule

module registru(input[3:0] a,input clk, output [3:0] out);
  
  bistabil_D b1(a,clk,out);
  bistabil_D b2(a[2],clk,out[2]);
  bistabil_D b3(a[1],clk,out[1]);
  bistabil_D b4(a[0],clk,out[0]);
endmodule
*/
module registru2(input[3:0] a,input clk, output reg[3:0] out);
  always @(posedge clk)
    begin
      out<=a;
    end
  
endmodule

tema1/pipo/testbench.sv
// Code your testbench here
// or browse Examples


module testbench();
  
  reg clk;
  reg [3:0]a;
  wire [3:0] O;
 
  registru2 Ichip1(a,clk,O);
  
  
  
  
  initial clk= 1'b0;
  initial a=4'b0000;
  
  initial forever #250 clk = ~clk;
	initial forever #1000 a=a+1'b1;
  initial begin
    $dumpfile("dump.vcd");
    $dumpvars;
   
    #9000;
    $finish(1);
  end
  
  
endmodule

tema1/pipo/dump.vcd
$date
	Tue Jun 27 15:31:12 2023
$end
$version
	Icarus Verilog
$end
$timescale
	1s
$end
$scope module testbench $end
$var wire 4 ! O [3:0] $end
$var reg 4 " a [3:0] $end
$var reg 1 # clk $end
$scope module Ichip1 $end
$var wire 4 $ a [3:0] $end
$var wire 1 % clk $end
$var reg 4 & out [3:0] $end
$upscope $end
$upscope $end
$enddefinitions $end
#0
$dumpvars
bx &
0%
b0 $
0#
b0 "
bx !
$end
#250
b0 &
b0 !
1#
1%
#500
0#
0%
#750
1#
1%
#1000
0#
0%
b1 "
b1 $
#1250
b1 &
b1 !
1#
1%
#1500
0#
0%
#1750
1#
1%
#2000
0#
0%
b10 "
b10 $
#2250
b10 &
b10 !
1#
1%
#2500
0#
0%
#2750
1#
1%
#3000
0#
0%
b11 "
b11 $
#3250
b11 &
b11 !
1#
1%
#3500
0#
0%
#3750
1#
1%
#4000
0#
0%
b100 "
b100 $
#4250
b100 &
b100 !
1#
1%
#4500
0#
0%
#4750
1#
1%
#5000
0#
0%
b101 "
b101 $
#5250
b101 &
b101 !
1#
1%
#5500
0#
0%
#5750
1#
1%
#6000
0#
0%
b110 "
b110 $
#6250
b110 &
b110 !
1#
1%
#6500
0#
0%
#6750
1#
1%
#7000
0#
0%
b111 "
b111 $
#7250
b111 &
b111 !
1#
1%
#7500
0#
0%
#7750
1#
1%
#8000
0#
0%
b1000 "
b1000 $
#8250
b1000 &
b1000 !
1#
1%
#8500
0#
0%
#8750
1#
1%
#9000
0#
0%
b1001 "
b1001 $
